linesim/__init__.py
linesim/beacons.py
linesim/linesim.py
linesim/sensors.py
linesim/assets/blank.png
linesim/assets/lines.png
linesim/assets/maze.png
linesim/assets/robot.png
linesim-0.2.2.dist-info/LICENSE
linesim-0.2.2.dist-info/METADATA
linesim-0.2.2.dist-info/WHEEL
linesim-0.2.2.dist-info/top_level.txt
linesim-0.2.2.dist-info/RECORD
