Metadata-Version: 2.1
Name: linesim
Version: 0.2.2
Summary: A package allowing testing of line following code
Author-email: Eduard Tanase <eduard.tanase1@gmail.com>
Project-URL: Homepage, https://github.com/meme8383/linesim
Project-URL: Bug Tracker, https://github.com/meme8383/linesim/issues
Classifier: Programming Language :: Python :: 3
Classifier: License :: OSI Approved :: MIT License
Classifier: Operating System :: OS Independent
Requires-Python: >=3.7
License-File: LICENSE
Requires-Dist: pygame (>=2.1.2) ; python_version < "3.11"
Requires-Dist: pygame (>=2.1.3-dev8) ; python_version >= "3.11"
